helloworld.py
helloworld_tspeer-0.0.1.dist-info/LICENSE.txt
helloworld_tspeer-0.0.1.dist-info/METADATA
helloworld_tspeer-0.0.1.dist-info/WHEEL
helloworld_tspeer-0.0.1.dist-info/top_level.txt
helloworld_tspeer-0.0.1.dist-info/RECORD
